trust_plutus_namematch/__init__.py
trust_plutus_namematch/match.py
trust_plutus_namematch/utils/__init__.py
trust_plutus_namematch/utils/logs.py
trust_plutus_namematch-3.0.1.dist-info/LICENSE
trust_plutus_namematch-3.0.1.dist-info/METADATA
trust_plutus_namematch-3.0.1.dist-info/WHEEL
trust_plutus_namematch-3.0.1.dist-info/RECORD
