Metadata-Version: 2.1
Name: trust-plutus-namematch
Version: 3.0.1
Summary: Name match for fund names from ICRA and MILES
License: OSI Approved :: GNU General Public License v3 (GPLv3)
Author: Rolf Lobo
Requires-Python: >=3.10,<3.11
Classifier: License :: Other/Proprietary License
Classifier: Programming Language :: Python :: 3
Classifier: Programming Language :: Python :: 3.10
Requires-Dist: joblib (>=1.4.2,<2.0.0)
Requires-Dist: loga (>=1.0.0,<2.0.0)
Requires-Dist: numpy (==1.23.1)
Requires-Dist: openpyxl (==3.0.10)
Requires-Dist: pandas (==1.4.3)
Requires-Dist: rapidfuzz (==3.9.0)
